pytest_socket.pth
pytest_socket/__init__.py
pytest_socket/_core.py
pytest_socket/_plugin.py
pytest_subket-0.8.2.dist-info/licenses/LICENSE
pytest_subket-0.8.2.dist-info/METADATA
pytest_subket-0.8.2.dist-info/WHEEL
pytest_subket-0.8.2.dist-info/entry_points.txt
pytest_subket-0.8.2.dist-info/top_level.txt
pytest_subket-0.8.2.dist-info/RECORD
