Metadata-Version: 2.4
Name: pytest-subket
Version: 0.8.2
Summary: Pytest Plugin to disable socket calls during tests
Author-email: Mike Fiedler <miketheman@gmail.com>, Richard Si <sichard26@gmail.com>
License-Expression: MIT
Project-URL: Homepage, https://pypi.org/project/pytest-subket/
Project-URL: Repository, https://github.com/ichard26/pytest-subket
Project-URL: Change Log, https://github.com/ichard26/pytest-subket/blob/main/CHANGELOG.md
Classifier: Development Status :: 4 - Beta
Classifier: Framework :: Pytest
Classifier: Intended Audience :: Developers
Classifier: Topic :: Software Development :: Testing
Classifier: Programming Language :: Python
Classifier: Programming Language :: Python :: 3.9
Classifier: Programming Language :: Python :: 3.10
Classifier: Programming Language :: Python :: 3.11
Classifier: Programming Language :: Python :: 3.12
Classifier: Programming Language :: Python :: 3.13
Classifier: Programming Language :: Python :: Implementation :: CPython
Classifier: Operating System :: OS Independent
Requires-Python: >=3.9
License-File: LICENSE
Provides-Extra: dev
Requires-Dist: pytest-httpbin>=2.1.0; extra == "dev"
Requires-Dist: pytest-randomly>=3.15.0; extra == "dev"
Requires-Dist: requests>=2.32.4; extra == "dev"
Requires-Dist: starlette>=0.47.1; extra == "dev"
Requires-Dist: httpx>=0.28.1; extra == "dev"
Dynamic: license-file
